docs/clean.py
docs/conf.py
examples/conversation_of_reply_search.py
examples/find_tweet_by_id.py
examples/fullarchive_search.py
examples/hydrator.py
examples/pagination.py
examples/process.py
examples/search_stream.py
examples/temp.py
tweetkit/__init__.py
tweetkit/auth.py
tweetkit/client.py
tweetkit/exceptions.py
tweetkit/models/__init__.py
tweetkit/models/expansions.py
tweetkit/models/paginator.py
tweetkit/models/request.py
tweetkit/models/response.py
tweetkit/requests/__init__.py
tweetkit/requests/bookmarks.py
tweetkit/requests/compliance.py
tweetkit/requests/general.py
tweetkit/requests/lists.py
tweetkit/requests/spaces.py
tweetkit/requests/tweets.py
tweetkit/requests/users.py
tweetkit/utils/__init__.py
tweetkit/utils/copy.py
tweetkit/utils/json.py
venv/bin/activate_this.py
venv/bin/rst2html.py
venv/bin/rst2html4.py
venv/bin/rst2html5.py
venv/bin/rst2latex.py
venv/bin/rst2man.py
venv/bin/rst2odt.py
venv/bin/rst2odt_prepstyles.py
venv/bin/rst2pseudoxml.py
venv/bin/rst2s5.py
venv/bin/rst2xetex.py
venv/bin/rst2xml.py
venv/bin/rstpep2html.py
tweetkit-0.2.8.dist-info/LICENSE.md
tweetkit-0.2.8.dist-info/METADATA
tweetkit-0.2.8.dist-info/WHEEL
tweetkit-0.2.8.dist-info/top_level.txt
tweetkit-0.2.8.dist-info/RECORD
