Metadata-Version: 2.1
Name: tweetkit
Version: 0.2.8
Summary: TweetKit
Classifier: Programming Language :: Python :: 3
Classifier: License :: OSI Approved :: MIT License
Classifier: Operating System :: OS Independent
Requires-Python: >=3.7
License-File: LICENSE.md
Requires-Dist: requests (>=2.27)
Requires-Dist: oauthlib (>=3.2)
Requires-Dist: requests-oauthlib (>=1.3)
Provides-Extra: dev
Requires-Dist: pytest ; extra == 'dev'
Requires-Dist: pip-tools ; extra == 'dev'
Requires-Dist: build ; extra == 'dev'
